{
    "version": "0.2.17",
    "architecture": {
        "64bit": {
            "url": "https://github.com/muthuishere/lnb/releases/download/v0.2.17/lnb_0.2.17_Windows_x86_64.tar.gz",
            "bin": [
                "lnb.exe"
            ],
            "hash": "6ff755b0703d2fd886572db18ea531522f7be88827079d862678a987f410cd7f"
        }
    },
    "homepage": "https://github.com/muthuishere/lnb",
    "license": "MIT",
    "description": "A cross-platform utility that makes command-line tools accessible from anywhere by creating symbolic links or wrapper scripts in your system's PATH"
}