{
    "version": "0.3.14",
    "architecture": {
        "64bit": {
            "url": "https://github.com/muthuishere/lnb/releases/download/v0.3.14/lnb_0.3.14_Windows_x86_64.tar.gz",
            "bin": [
                "lnb.exe"
            ],
            "hash": "f64475413bc86bd0ce508740580b4426359928a351e3b11e1c31b40dc5b56c16"
        }
    },
    "homepage": "https://github.com/muthuishere/lnb",
    "license": "MIT",
    "description": "A cross-platform utility that makes command-line tools accessible from anywhere by creating symbolic links or wrapper scripts in your system's PATH"
}